{
  "tipo": "giornaliero",
  "data_pubblicazione": "2026-07-18",
  "ora_pubblicazione": "07:00",
  "titolo_evento": "25° Rally Bianco Azzurro",
  "caption": "🏎 Il Rally Bianco Azzurro torna a rombare sulle strade del Titano, 25ª edizione. Gran finale domenica pomeriggio con arrivo e premiazioni in Piazza della Pace, a Montegiardino.\n\n👉 Tutti gli altri eventi di oggi nelle nostre storie.\nSalva il post 📌 e seguici per non perdere gli eventi di San Marino.\nℹ️ Date e orari possono cambiare: verifica sempre sulla fonte ufficiale dell'organizzatore (link in bio).\n\n#SanMarinoHappens #SanMarino #RepubblicaDiSanMarino #MonteTitano #cosafareaSanMarino #eventiSanMarino #RallyBiancoAzzurro #Montegiardino #Rally"
}
